thomasfermi/FQHE.py
thomasfermi/algo.py
thomasfermi/nu_to_mu.dat
thomasfermi/phi.py
thomasfermi-0.9.dist-info/LICENSE
thomasfermi-0.9.dist-info/METADATA
thomasfermi-0.9.dist-info/WHEEL
thomasfermi-0.9.dist-info/top_level.txt
thomasfermi-0.9.dist-info/zip-safe
thomasfermi-0.9.dist-info/RECORD
